.gitignore
bootstrap.py
buildout.cfg
setup.py
docs/Makefile
docs/changes.txt
docs/conf.py
docs/description.txt
docs/development.txt
docs/index.txt
docs/installation.txt
docs/license.txt
docs/make.bat
docs/use.txt
nose_fixes/__init__.py
nose_fixes/compat.py
nose_fixes/plugin.py
nose_fixes.egg-info/PKG-INFO
nose_fixes.egg-info/SOURCES.txt
nose_fixes.egg-info/dependency_links.txt
nose_fixes.egg-info/entry_points.txt
nose_fixes.egg-info/not-zip-safe
nose_fixes.egg-info/requires.txt
nose_fixes.egg-info/top_level.txt
nose_fixes/tests/__init__.py
nose_fixes/tests/test_collection.py
nose_fixes/tests/test_docstrings.py
nose_fixes/tests/test_plugin.py