Metadata-Version: 1.1
Name: nose_fixes
Version: 1.3
Summary: A plugin to make nose behave better.
Home-page: http://packages.python.org/nose_fixes
Author: Chris Withers
Author-email: chris@simplistix.co.uk
License: MIT
Platform: UNKNOWN
Classifier: Development Status :: 5 - Production/Stable
Classifier: Intended Audience :: Developers
Classifier: License :: OSI Approved :: MIT License
